quantify_qblox/__init__.py
quantify_qblox/quantify_qblox.py
quantify_qblox-0.0.1.dist-info/METADATA
quantify_qblox-0.0.1.dist-info/WHEEL
quantify_qblox-0.0.1.dist-info/top_level.txt
quantify_qblox-0.0.1.dist-info/RECORD
