Metadata-Version: 2.1
Name: quantify-qblox
Version: 0.0.1
Summary: Qblox backend for Quantify
Project-URL: Homepage, https://qblox.com
Keywords: qblox,quantify,quantum
Classifier: Development Status :: 4 - Beta
Classifier: Intended Audience :: Developers
Classifier: Intended Audience :: Science/Research
Classifier: License :: OSI Approved :: BSD License
Classifier: Natural Language :: English
Classifier: Programming Language :: Python :: 3
Classifier: Programming Language :: Python :: 3.8
Classifier: Programming Language :: Python :: 3.9
Classifier: Topic :: Scientific/Engineering
Requires-Python: <3.10,>=3.8
Provides-Extra: dev
Provides-Extra: test
